<annotation>
	<folder>train</folder>
	<filename>14.jpg</filename>
	<path>D:\Users\doria\Documents\Travail\Ecole d'ingénieur\Ecole EFREI\M1\Big Data Machine Learning\Projet\Training_project\models\research\object_detection\images\train\14.jpg</path>
	<source>
		<database>Unknown</database>
	</source>
	<size>
		<width>1700</width>
		<height>2340</height>
		<depth>3</depth>
	</size>
	<segmented>0</segmented>
	<object>
		<name>charlie</name>
		<pose>Unspecified</pose>
		<truncated>0</truncated>
		<difficult>0</difficult>
		<bndbox>
			<xmin>191</xmin>
			<ymin>1873</ymin>
			<xmax>238</xmax>
			<ymax>1925</ymax>
		</bndbox>
	</object>
</annotation>
