<annotation>
	<folder>train</folder>
	<filename>20.jpg</filename>
	<path>D:\Users\doria\Documents\Travail\Ecole d'ingénieur\Ecole EFREI\M1\Big Data Machine Learning\Projet\Training_project\models\research\object_detection\images\train\20.jpg</path>
	<source>
		<database>Unknown</database>
	</source>
	<size>
		<width>2953</width>
		<height>2088</height>
		<depth>3</depth>
	</size>
	<segmented>0</segmented>
	<object>
		<name>charlie</name>
		<pose>Unspecified</pose>
		<truncated>0</truncated>
		<difficult>0</difficult>
		<bndbox>
			<xmin>288</xmin>
			<ymin>1679</ymin>
			<xmax>332</xmax>
			<ymax>1732</ymax>
		</bndbox>
	</object>
</annotation>
